[
  {
    "id": "8ab15f8c-286c-49d1-92f2-18cf1776a001",
    "year": 2025,
    "make": "land-rover",
    "model": "range-rover-velar",
    "trim": "Base",
    "status": "verified",
    "reason": "Specifications match known values",
    "verifiedBoltPattern": "5x120",
    "verifiedHubBore": "72.6",
    "verifiedWheelSizes": [
      {
        "axle": "square",
        "width": 8.5,
        "isStock": true,
        "diameter": 19
      },
      {
        "axle": "square",
        "width": 9,
        "isStock": true,
        "diameter": 20
      },
      {
        "axle": "square",
        "width": 9.5,
        "isStock": true,
        "diameter": 21
      },
      {
        "axle": "square",
        "width": 10,
        "isStock": true,
        "diameter": 22
      }
    ],
    "verifiedTireSizes": [
      "255/55R19",
      "275/45R20",
      "275/40R21",
      "285/35R22"
    ],
    "sources": [
      "tiresize.com",
      "industry-standard-specs"
    ]
  },
  {
    "id": "b589faf6-f0d0-43c2-871d-d16b844a96c8",
    "year": 2026,
    "make": "land-rover",
    "model": "range-rover-velar",
    "trim": "Base",
    "status": "verified",
    "reason": "Specifications match known values",
    "verifiedBoltPattern": "5x120",
    "verifiedHubBore": "72.6",
    "verifiedWheelSizes": [
      {
        "axle": "square",
        "width": 8.5,
        "isStock": true,
        "diameter": 19
      },
      {
        "axle": "square",
        "width": 9,
        "isStock": true,
        "diameter": 20
      },
      {
        "axle": "square",
        "width": 9.5,
        "isStock": true,
        "diameter": 21
      },
      {
        "axle": "square",
        "width": 10,
        "isStock": true,
        "diameter": 22
      }
    ],
    "verifiedTireSizes": [
      "255/55R19",
      "275/45R20",
      "275/40R21",
      "285/35R22"
    ],
    "sources": [
      "tiresize.com",
      "industry-standard-specs"
    ]
  }
]