{
  "batchId": "80s-gm-sedans",
  "completedAt": "2026-04-22T09:41:00Z",
  "totalVehicles": 156,
  "successCount": 156,
  "failureCount": 0,
  "vehicles": [
    {
      "year": 1980, "make": "Chevrolet", "model": "Caprice",
      "bolt_pattern": "5x127",
      "hub_bore": 78.1,
      "oem_wheel_sizes": ["15x6", "15x7"],
      "oem_tire_sizes": ["205/75R15", "225/70R15"],
      "staggered": false,
      "sources": ["tiresize.com", "roadkillcustoms.com"],
      "confidence": "high",
      "notes": "B-body RWD platform"
    },
    {
      "year": 1981, "make": "Chevrolet", "model": "Caprice",
      "bolt_pattern": "5x127",
      "hub_bore": 78.1,
      "oem_wheel_sizes": ["15x6", "15x7"],
      "oem_tire_sizes": ["205/75R15", "225/70R15"],
      "staggered": false,
      "sources": ["tiresize.com", "roadkillcustoms.com"],
      "confidence": "high",
      "notes": "B-body RWD platform"
    },
    {
      "year": 1982, "make": "Chevrolet", "model": "Caprice",
      "bolt_pattern": "5x127",
      "hub_bore": 78.1,
      "oem_wheel_sizes": ["15x6", "15x7"],
      "oem_tire_sizes": ["205/75R15", "225/70R15"],
      "staggered": false,
      "sources": ["tiresize.com", "roadkillcustoms.com"],
      "confidence": "high",
      "notes": "B-body RWD platform"
    },
    {
      "year": 1983, "make": "Chevrolet", "model": "Caprice",
      "bolt_pattern": "5x127",
      "hub_bore": 78.1,
      "oem_wheel_sizes": ["15x6", "15x7"],
      "oem_tire_sizes": ["205/75R15", "225/70R15"],
      "staggered": false,
      "sources": ["tiresize.com", "roadkillcustoms.com"],
      "confidence": "high",
      "notes": "B-body RWD platform"
    },
    {
      "year": 1984, "make": "Chevrolet", "model": "Caprice",
      "bolt_pattern": "5x127",
      "hub_bore": 78.1,
      "oem_wheel_sizes": ["15x6", "15x7"],
      "oem_tire_sizes": ["205/75R15", "225/70R15"],
      "staggered": false,
      "sources": ["tiresize.com", "roadkillcustoms.com"],
      "confidence": "high",
      "notes": "B-body RWD platform"
    },
    {
      "year": 1985, "make": "Chevrolet", "model": "Caprice",
      "bolt_pattern": "5x127",
      "hub_bore": 78.1,
      "oem_wheel_sizes": ["15x6", "15x7"],
      "oem_tire_sizes": ["205/75R15", "225/70R15"],
      "staggered": false,
      "sources": ["tiresize.com", "roadkillcustoms.com"],
      "confidence": "high",
      "notes": "B-body RWD platform"
    },
    {
      "year": 1986, "make": "Chevrolet", "model": "Caprice",
      "bolt_pattern": "5x127",
      "hub_bore": 78.1,
      "oem_wheel_sizes": ["15x6", "15x7"],
      "oem_tire_sizes": ["205/75R15", "225/70R15"],
      "staggered": false,
      "sources": ["tiresize.com", "roadkillcustoms.com"],
      "confidence": "high",
      "notes": "B-body RWD platform"
    },
    {
      "year": 1987, "make": "Chevrolet", "model": "Caprice",
      "bolt_pattern": "5x127",
      "hub_bore": 78.1,
      "oem_wheel_sizes": ["15x6", "15x7"],
      "oem_tire_sizes": ["205/75R15", "225/70R15"],
      "staggered": false,
      "sources": ["tiresize.com", "roadkillcustoms.com"],
      "confidence": "high",
      "notes": "B-body RWD platform"
    },
    {
      "year": 1988, "make": "Chevrolet", "model": "Caprice",
      "bolt_pattern": "5x127",
      "hub_bore": 78.1,
      "oem_wheel_sizes": ["15x6", "15x7"],
      "oem_tire_sizes": ["205/75R15", "225/70R15"],
      "staggered": false,
      "sources": ["tiresize.com", "roadkillcustoms.com"],
      "confidence": "high",
      "notes": "B-body RWD platform"
    },
    {
      "year": 1989, "make": "Chevrolet", "model": "Caprice",
      "bolt_pattern": "5x127",
      "hub_bore": 78.1,
      "oem_wheel_sizes": ["15x6", "15x7"],
      "oem_tire_sizes": ["205/75R15", "225/70R15"],
      "staggered": false,
      "sources": ["tiresize.com", "roadkillcustoms.com"],
      "confidence": "high",
      "notes": "B-body RWD platform"
    },
    {
      "year": 1980, "make": "Chevrolet", "model": "Impala",
      "bolt_pattern": "5x127",
      "hub_bore": 78.1,
      "oem_wheel_sizes": ["15x6", "15x7"],
      "oem_tire_sizes": ["205/75R15", "225/70R15"],
      "staggered": false,
      "sources": ["tiresize.com", "impalaforums.com"],
      "confidence": "high",
      "notes": "B-body RWD platform, shares with Caprice"
    },
    {
      "year": 1981, "make": "Chevrolet", "model": "Impala",
      "bolt_pattern": "5x127",
      "hub_bore": 78.1,
      "oem_wheel_sizes": ["15x6", "15x7"],
      "oem_tire_sizes": ["205/75R15", "225/70R15"],
      "staggered": false,
      "sources": ["tiresize.com", "impalaforums.com"],
      "confidence": "high",
      "notes": "B-body RWD platform"
    },
    {
      "year": 1982, "make": "Chevrolet", "model": "Impala",
      "bolt_pattern": "5x127",
      "hub_bore": 78.1,
      "oem_wheel_sizes": ["15x6", "15x7"],
      "oem_tire_sizes": ["205/75R15", "225/70R15"],
      "staggered": false,
      "sources": ["tiresize.com", "impalaforums.com"],
      "confidence": "high",
      "notes": "B-body RWD platform"
    },
    {
      "year": 1983, "make": "Chevrolet", "model": "Impala",
      "bolt_pattern": "5x127",
      "hub_bore": 78.1,
      "oem_wheel_sizes": ["15x6", "15x7"],
      "oem_tire_sizes": ["205/75R15", "225/70R15"],
      "staggered": false,
      "sources": ["tiresize.com", "impalaforums.com"],
      "confidence": "high",
      "notes": "B-body RWD platform"
    },
    {
      "year": 1984, "make": "Chevrolet", "model": "Impala",
      "bolt_pattern": "5x127",
      "hub_bore": 78.1,
      "oem_wheel_sizes": ["15x6", "15x7"],
      "oem_tire_sizes": ["205/75R15", "225/70R15"],
      "staggered": false,
      "sources": ["tiresize.com", "impalaforums.com"],
      "confidence": "high",
      "notes": "B-body RWD platform"
    },
    {
      "year": 1985, "make": "Chevrolet", "model": "Impala",
      "bolt_pattern": "5x127",
      "hub_bore": 78.1,
      "oem_wheel_sizes": ["15x6", "15x7"],
      "oem_tire_sizes": ["205/75R15", "225/70R15"],
      "staggered": false,
      "sources": ["tiresize.com", "impalaforums.com"],
      "confidence": "high",
      "notes": "B-body RWD platform, last year for Impala until 1994"
    },
    {
      "year": 1982, "make": "Chevrolet", "model": "Celebrity",
      "bolt_pattern": "5x115",
      "hub_bore": 70.3,
      "oem_wheel_sizes": ["13x5.5", "14x6"],
      "oem_tire_sizes": ["185/80R13", "195/75R14"],
      "staggered": false,
      "sources": ["tiresize.com", "roadkillcustoms.com"],
      "confidence": "high",
      "notes": "A-body FWD platform"
    },
    {
      "year": 1983, "make": "Chevrolet", "model": "Celebrity",
      "bolt_pattern": "5x115",
      "hub_bore": 70.3,
      "oem_wheel_sizes": ["13x5.5", "14x6"],
      "oem_tire_sizes": ["185/80R13", "195/75R14"],
      "staggered": false,
      "sources": ["tiresize.com", "roadkillcustoms.com"],
      "confidence": "high",
      "notes": "A-body FWD platform"
    },
    {
      "year": 1984, "make": "Chevrolet", "model": "Celebrity",
      "bolt_pattern": "5x115",
      "hub_bore": 70.3,
      "oem_wheel_sizes": ["14x6"],
      "oem_tire_sizes": ["195/75R14"],
      "staggered": false,
      "sources": ["tiresize.com", "roadkillcustoms.com"],
      "confidence": "high",
      "notes": "A-body FWD platform"
    },
    {
      "year": 1985, "make": "Chevrolet", "model": "Celebrity",
      "bolt_pattern": "5x115",
      "hub_bore": 70.3,
      "oem_wheel_sizes": ["14x6"],
      "oem_tire_sizes": ["185/75R14", "195/75R14"],
      "staggered": false,
      "sources": ["tiresize.com", "roadkillcustoms.com"],
      "confidence": "high",
      "notes": "A-body FWD platform"
    },
    {
      "year": 1986, "make": "Chevrolet", "model": "Celebrity",
      "bolt_pattern": "5x115",
      "hub_bore": 70.3,
      "oem_wheel_sizes": ["14x6"],
      "oem_tire_sizes": ["185/75R14", "195/75R14"],
      "staggered": false,
      "sources": ["tiresize.com", "roadkillcustoms.com"],
      "confidence": "high",
      "notes": "A-body FWD platform"
    },
    {
      "year": 1987, "make": "Chevrolet", "model": "Celebrity",
      "bolt_pattern": "5x115",
      "hub_bore": 70.3,
      "oem_wheel_sizes": ["14x6"],
      "oem_tire_sizes": ["185/75R14", "195/75R14"],
      "staggered": false,
      "sources": ["tiresize.com", "roadkillcustoms.com"],
      "confidence": "high",
      "notes": "A-body FWD platform"
    },
    {
      "year": 1988, "make": "Chevrolet", "model": "Celebrity",
      "bolt_pattern": "5x115",
      "hub_bore": 70.3,
      "oem_wheel_sizes": ["14x6"],
      "oem_tire_sizes": ["185/75R14", "195/70R14"],
      "staggered": false,
      "sources": ["tiresize.com", "roadkillcustoms.com"],
      "confidence": "high",
      "notes": "A-body FWD platform"
    },
    {
      "year": 1989, "make": "Chevrolet", "model": "Celebrity",
      "bolt_pattern": "5x115",
      "hub_bore": 70.3,
      "oem_wheel_sizes": ["14x6"],
      "oem_tire_sizes": ["185/75R14", "195/70R14"],
      "staggered": false,
      "sources": ["tiresize.com", "roadkillcustoms.com"],
      "confidence": "high",
      "notes": "A-body FWD platform"
    },
    {
      "year": 1982, "make": "Chevrolet", "model": "Cavalier",
      "bolt_pattern": "5x100",
      "hub_bore": 57.1,
      "oem_wheel_sizes": ["13x5.5"],
      "oem_tire_sizes": ["175/80R13"],
      "staggered": false,
      "sources": ["tiresize.com", "tirewheelguide.com"],
      "confidence": "high",
      "notes": "J-body platform"
    },
    {
      "year": 1983, "make": "Chevrolet", "model": "Cavalier",
      "bolt_pattern": "5x100",
      "hub_bore": 57.1,
      "oem_wheel_sizes": ["13x5.5"],
      "oem_tire_sizes": ["175/80R13"],
      "staggered": false,
      "sources": ["tiresize.com", "tirewheelguide.com"],
      "confidence": "high",
      "notes": "J-body platform"
    },
    {
      "year": 1984, "make": "Chevrolet", "model": "Cavalier",
      "bolt_pattern": "5x100",
      "hub_bore": 57.1,
      "oem_wheel_sizes": ["13x5.5"],
      "oem_tire_sizes": ["175/80R13"],
      "staggered": false,
      "sources": ["tiresize.com", "tirewheelguide.com"],
      "confidence": "high",
      "notes": "J-body platform"
    },
    {
      "year": 1985, "make": "Chevrolet", "model": "Cavalier",
      "bolt_pattern": "5x100",
      "hub_bore": 57.1,
      "oem_wheel_sizes": ["13x5.5", "14x6"],
      "oem_tire_sizes": ["175/80R13", "215/60R14"],
      "staggered": false,
      "sources": ["tiresize.com", "tirewheelguide.com"],
      "confidence": "high",
      "notes": "J-body platform, Z24 has 14-inch option"
    },
    {
      "year": 1986, "make": "Chevrolet", "model": "Cavalier",
      "bolt_pattern": "5x100",
      "hub_bore": 57.1,
      "oem_wheel_sizes": ["13x5.5", "14x6"],
      "oem_tire_sizes": ["175/80R13", "215/60R14"],
      "staggered": false,
      "sources": ["tiresize.com", "tirewheelguide.com"],
      "confidence": "high",
      "notes": "J-body platform"
    },
    {
      "year": 1987, "make": "Chevrolet", "model": "Cavalier",
      "bolt_pattern": "5x100",
      "hub_bore": 57.1,
      "oem_wheel_sizes": ["13x5.5", "14x6"],
      "oem_tire_sizes": ["175/80R13", "215/60R14"],
      "staggered": false,
      "sources": ["tiresize.com", "tirewheelguide.com"],
      "confidence": "high",
      "notes": "J-body platform"
    },
    {
      "year": 1988, "make": "Chevrolet", "model": "Cavalier",
      "bolt_pattern": "5x100",
      "hub_bore": 57.1,
      "oem_wheel_sizes": ["13x5.5", "14x6"],
      "oem_tire_sizes": ["185/80R13", "195/70R14", "215/60R14"],
      "staggered": false,
      "sources": ["tiresize.com", "tirewheelguide.com"],
      "confidence": "high",
      "notes": "J-body platform, refreshed model year"
    },
    {
      "year": 1989, "make": "Chevrolet", "model": "Cavalier",
      "bolt_pattern": "5x100",
      "hub_bore": 57.1,
      "oem_wheel_sizes": ["13x5.5", "14x6"],
      "oem_tire_sizes": ["185/80R13", "195/70R14", "215/60R14"],
      "staggered": false,
      "sources": ["tiresize.com", "tirewheelguide.com"],
      "confidence": "high",
      "notes": "J-body platform"
    },
    {
      "year": 1980, "make": "Pontiac", "model": "Bonneville",
      "bolt_pattern": "5x127",
      "hub_bore": 78.1,
      "oem_wheel_sizes": ["15x6", "15x7"],
      "oem_tire_sizes": ["205/75R15", "225/70R15"],
      "staggered": false,
      "sources": ["roadkillcustoms.com", "tiresize.com"],
      "confidence": "high",
      "notes": "B-body RWD platform"
    },
    {
      "year": 1981, "make": "Pontiac", "model": "Bonneville",
      "bolt_pattern": "5x127",
      "hub_bore": 78.1,
      "oem_wheel_sizes": ["15x6", "15x7"],
      "oem_tire_sizes": ["205/75R15", "225/70R15"],
      "staggered": false,
      "sources": ["roadkillcustoms.com", "tiresize.com"],
      "confidence": "high",
      "notes": "B-body RWD platform, last year before G-body"
    },
    {
      "year": 1982, "make": "Pontiac", "model": "Bonneville",
      "bolt_pattern": "5x120.65",
      "hub_bore": 70.3,
      "oem_wheel_sizes": ["14x6"],
      "oem_tire_sizes": ["195/75R14", "205/70R14"],
      "staggered": false,
      "sources": ["roadkillcustoms.com", "tiresize.com"],
      "confidence": "high",
      "notes": "G-body platform (downsized)"
    },
    {
      "year": 1983, "make": "Pontiac", "model": "Bonneville",
      "bolt_pattern": "5x120.65",
      "hub_bore": 70.3,
      "oem_wheel_sizes": ["14x6"],
      "oem_tire_sizes": ["195/75R14", "205/70R14"],
      "staggered": false,
      "sources": ["roadkillcustoms.com", "tiresize.com"],
      "confidence": "high",
      "notes": "G-body platform"
    },
    {
      "year": 1984, "make": "Pontiac", "model": "Bonneville",
      "bolt_pattern": "5x120.65",
      "hub_bore": 70.3,
      "oem_wheel_sizes": ["14x6"],
      "oem_tire_sizes": ["195/75R14", "205/70R14"],
      "staggered": false,
      "sources": ["roadkillcustoms.com", "tiresize.com"],
      "confidence": "high",
      "notes": "G-body platform"
    },
    {
      "year": 1985, "make": "Pontiac", "model": "Bonneville",
      "bolt_pattern": "5x120.65",
      "hub_bore": 70.3,
      "oem_wheel_sizes": ["14x6"],
      "oem_tire_sizes": ["195/75R14", "205/70R14"],
      "staggered": false,
      "sources": ["roadkillcustoms.com", "tiresize.com"],
      "confidence": "high",
      "notes": "G-body platform"
    },
    {
      "year": 1986, "make": "Pontiac", "model": "Bonneville",
      "bolt_pattern": "5x120.65",
      "hub_bore": 70.3,
      "oem_wheel_sizes": ["14x6"],
      "oem_tire_sizes": ["195/75R14", "205/70R14"],
      "staggered": false,
      "sources": ["roadkillcustoms.com", "tiresize.com"],
      "confidence": "high",
      "notes": "G-body platform, last year"
    },
    {
      "year": 1987, "make": "Pontiac", "model": "Bonneville",
      "bolt_pattern": "5x115",
      "hub_bore": 70.3,
      "oem_wheel_sizes": ["14x6", "15x6"],
      "oem_tire_sizes": ["195/75R14", "205/70R14", "195/70R15"],
      "staggered": false,
      "sources": ["roadkillcustoms.com", "tiresize.com"],
      "confidence": "high",
      "notes": "H-body FWD platform"
    },
    {
      "year": 1988, "make": "Pontiac", "model": "Bonneville",
      "bolt_pattern": "5x115",
      "hub_bore": 70.3,
      "oem_wheel_sizes": ["15x6"],
      "oem_tire_sizes": ["195/70R15", "205/70R15"],
      "staggered": false,
      "sources": ["roadkillcustoms.com", "tiresize.com"],
      "confidence": "high",
      "notes": "H-body FWD platform"
    },
    {
      "year": 1989, "make": "Pontiac", "model": "Bonneville",
      "bolt_pattern": "5x115",
      "hub_bore": 70.3,
      "oem_wheel_sizes": ["15x6"],
      "oem_tire_sizes": ["195/70R15", "205/70R15"],
      "staggered": false,
      "sources": ["roadkillcustoms.com", "tiresize.com"],
      "confidence": "high",
      "notes": "H-body FWD platform"
    },
    {
      "year": 1982, "make": "Pontiac", "model": "6000",
      "bolt_pattern": "5x115",
      "hub_bore": 70.3,
      "oem_wheel_sizes": ["13x5.5", "14x6"],
      "oem_tire_sizes": ["185/80R13", "195/75R14"],
      "staggered": false,
      "sources": ["roadkillcustoms.com", "tiresize.com"],
      "confidence": "high",
      "notes": "A-body FWD platform"
    },
    {
      "year": 1983, "make": "Pontiac", "model": "6000",
      "bolt_pattern": "5x115",
      "hub_bore": 70.3,
      "oem_wheel_sizes": ["13x5.5", "14x6"],
      "oem_tire_sizes": ["185/80R13", "195/75R14"],
      "staggered": false,
      "sources": ["roadkillcustoms.com", "tiresize.com"],
      "confidence": "high",
      "notes": "A-body FWD platform"
    },
    {
      "year": 1984, "make": "Pontiac", "model": "6000",
      "bolt_pattern": "5x115",
      "hub_bore": 70.3,
      "oem_wheel_sizes": ["14x6"],
      "oem_tire_sizes": ["185/75R14", "195/75R14"],
      "staggered": false,
      "sources": ["roadkillcustoms.com", "tiresize.com"],
      "confidence": "high",
      "notes": "A-body FWD platform"
    },
    {
      "year": 1985, "make": "Pontiac", "model": "6000",
      "bolt_pattern": "5x115",
      "hub_bore": 70.3,
      "oem_wheel_sizes": ["14x6"],
      "oem_tire_sizes": ["185/75R14", "195/75R14"],
      "staggered": false,
      "sources": ["roadkillcustoms.com", "tiresize.com"],
      "confidence": "high",
      "notes": "A-body FWD platform"
    },
    {
      "year": 1986, "make": "Pontiac", "model": "6000",
      "bolt_pattern": "5x115",
      "hub_bore": 70.3,
      "oem_wheel_sizes": ["14x6"],
      "oem_tire_sizes": ["185/75R14", "195/75R14"],
      "staggered": false,
      "sources": ["roadkillcustoms.com", "tiresize.com"],
      "confidence": "high",
      "notes": "A-body FWD platform"
    },
    {
      "year": 1987, "make": "Pontiac", "model": "6000",
      "bolt_pattern": "5x115",
      "hub_bore": 70.3,
      "oem_wheel_sizes": ["14x6"],
      "oem_tire_sizes": ["185/75R14", "195/75R14"],
      "staggered": false,
      "sources": ["roadkillcustoms.com", "tiresize.com"],
      "confidence": "high",
      "notes": "A-body FWD platform"
    },
    {
      "year": 1988, "make": "Pontiac", "model": "6000",
      "bolt_pattern": "5x115",
      "hub_bore": 70.3,
      "oem_wheel_sizes": ["14x6"],
      "oem_tire_sizes": ["185/75R14", "195/75R14"],
      "staggered": false,
      "sources": ["roadkillcustoms.com", "tiresize.com"],
      "confidence": "high",
      "notes": "A-body FWD platform"
    },
    {
      "year": 1989, "make": "Pontiac", "model": "6000",
      "bolt_pattern": "5x115",
      "hub_bore": 70.3,
      "oem_wheel_sizes": ["14x6"],
      "oem_tire_sizes": ["185/75R14", "195/75R14"],
      "staggered": false,
      "sources": ["roadkillcustoms.com", "tiresize.com"],
      "confidence": "high",
      "notes": "A-body FWD platform, also had AWD STE option"
    },
    {
      "year": 1980, "make": "Buick", "model": "LeSabre",
      "bolt_pattern": "5x127",
      "hub_bore": 78.1,
      "oem_wheel_sizes": ["15x6", "15x7"],
      "oem_tire_sizes": ["205/75R15", "215/75R15"],
      "staggered": false,
      "sources": ["roadkillcustoms.com", "tiresize.com"],
      "confidence": "high",
      "notes": "B-body RWD platform"
    },
    {
      "year": 1981, "make": "Buick", "model": "LeSabre",
      "bolt_pattern": "5x127",
      "hub_bore": 78.1,
      "oem_wheel_sizes": ["15x6", "15x7"],
      "oem_tire_sizes": ["205/75R15", "215/75R15"],
      "staggered": false,
      "sources": ["roadkillcustoms.com", "tiresize.com"],
      "confidence": "high",
      "notes": "B-body RWD platform"
    },
    {
      "year": 1982, "make": "Buick", "model": "LeSabre",
      "bolt_pattern": "5x127",
      "hub_bore": 78.1,
      "oem_wheel_sizes": ["15x6", "15x7"],
      "oem_tire_sizes": ["205/75R15", "215/75R15"],
      "staggered": false,
      "sources": ["roadkillcustoms.com", "tiresize.com"],
      "confidence": "high",
      "notes": "B-body RWD platform"
    },
    {
      "year": 1983, "make": "Buick", "model": "LeSabre",
      "bolt_pattern": "5x127",
      "hub_bore": 78.1,
      "oem_wheel_sizes": ["15x6", "15x7"],
      "oem_tire_sizes": ["205/75R15", "215/75R15"],
      "staggered": false,
      "sources": ["roadkillcustoms.com", "tiresize.com"],
      "confidence": "high",
      "notes": "B-body RWD platform"
    },
    {
      "year": 1984, "make": "Buick", "model": "LeSabre",
      "bolt_pattern": "5x127",
      "hub_bore": 78.1,
      "oem_wheel_sizes": ["15x6", "15x7"],
      "oem_tire_sizes": ["205/75R15", "215/75R15"],
      "staggered": false,
      "sources": ["roadkillcustoms.com", "tiresize.com"],
      "confidence": "high",
      "notes": "B-body RWD platform"
    },
    {
      "year": 1985, "make": "Buick", "model": "LeSabre",
      "bolt_pattern": "5x127",
      "hub_bore": 78.1,
      "oem_wheel_sizes": ["15x6", "15x7"],
      "oem_tire_sizes": ["205/75R15", "215/75R15"],
      "staggered": false,
      "sources": ["roadkillcustoms.com", "tiresize.com"],
      "confidence": "high",
      "notes": "B-body RWD platform, last year"
    },
    {
      "year": 1986, "make": "Buick", "model": "LeSabre",
      "bolt_pattern": "5x115",
      "hub_bore": 70.3,
      "oem_wheel_sizes": ["14x6", "15x6"],
      "oem_tire_sizes": ["195/75R14", "205/70R15"],
      "staggered": false,
      "sources": ["roadkillcustoms.com", "tiresize.com"],
      "confidence": "high",
      "notes": "H-body FWD platform"
    },
    {
      "year": 1987, "make": "Buick", "model": "LeSabre",
      "bolt_pattern": "5x115",
      "hub_bore": 70.3,
      "oem_wheel_sizes": ["14x6", "15x6"],
      "oem_tire_sizes": ["195/75R14", "205/70R15"],
      "staggered": false,
      "sources": ["roadkillcustoms.com", "tiresize.com"],
      "confidence": "high",
      "notes": "H-body FWD platform"
    },
    {
      "year": 1988, "make": "Buick", "model": "LeSabre",
      "bolt_pattern": "5x115",
      "hub_bore": 70.3,
      "oem_wheel_sizes": ["15x6"],
      "oem_tire_sizes": ["205/70R15"],
      "staggered": false,
      "sources": ["roadkillcustoms.com", "tiresize.com"],
      "confidence": "high",
      "notes": "H-body FWD platform"
    },
    {
      "year": 1989, "make": "Buick", "model": "LeSabre",
      "bolt_pattern": "5x115",
      "hub_bore": 70.3,
      "oem_wheel_sizes": ["15x6"],
      "oem_tire_sizes": ["205/70R15"],
      "staggered": false,
      "sources": ["roadkillcustoms.com", "tiresize.com"],
      "confidence": "high",
      "notes": "H-body FWD platform"
    },
    {
      "year": 1982, "make": "Buick", "model": "Century",
      "bolt_pattern": "5x115",
      "hub_bore": 70.3,
      "oem_wheel_sizes": ["13x5.5", "14x6"],
      "oem_tire_sizes": ["185/80R13", "195/75R14"],
      "staggered": false,
      "sources": ["roadkillcustoms.com", "tiresize.com"],
      "confidence": "high",
      "notes": "A-body FWD platform"
    },
    {
      "year": 1983, "make": "Buick", "model": "Century",
      "bolt_pattern": "5x115",
      "hub_bore": 70.3,
      "oem_wheel_sizes": ["14x6"],
      "oem_tire_sizes": ["185/75R14", "195/75R14"],
      "staggered": false,
      "sources": ["roadkillcustoms.com", "tiresize.com"],
      "confidence": "high",
      "notes": "A-body FWD platform"
    },
    {
      "year": 1984, "make": "Buick", "model": "Century",
      "bolt_pattern": "5x115",
      "hub_bore": 70.3,
      "oem_wheel_sizes": ["14x6"],
      "oem_tire_sizes": ["185/75R14", "195/75R14"],
      "staggered": false,
      "sources": ["roadkillcustoms.com", "tiresize.com"],
      "confidence": "high",
      "notes": "A-body FWD platform"
    },
    {
      "year": 1985, "make": "Buick", "model": "Century",
      "bolt_pattern": "5x115",
      "hub_bore": 70.3,
      "oem_wheel_sizes": ["14x6"],
      "oem_tire_sizes": ["185/75R14", "195/75R14"],
      "staggered": false,
      "sources": ["roadkillcustoms.com", "tiresize.com"],
      "confidence": "high",
      "notes": "A-body FWD platform"
    },
    {
      "year": 1986, "make": "Buick", "model": "Century",
      "bolt_pattern": "5x115",
      "hub_bore": 70.3,
      "oem_wheel_sizes": ["14x6"],
      "oem_tire_sizes": ["185/75R14", "195/75R14"],
      "staggered": false,
      "sources": ["roadkillcustoms.com", "tiresize.com"],
      "confidence": "high",
      "notes": "A-body FWD platform"
    },
    {
      "year": 1987, "make": "Buick", "model": "Century",
      "bolt_pattern": "5x115",
      "hub_bore": 70.3,
      "oem_wheel_sizes": ["14x6"],
      "oem_tire_sizes": ["185/75R14", "195/75R14"],
      "staggered": false,
      "sources": ["roadkillcustoms.com", "tiresize.com"],
      "confidence": "high",
      "notes": "A-body FWD platform"
    },
    {
      "year": 1988, "make": "Buick", "model": "Century",
      "bolt_pattern": "5x115",
      "hub_bore": 70.3,
      "oem_wheel_sizes": ["14x6"],
      "oem_tire_sizes": ["185/75R14", "195/75R14"],
      "staggered": false,
      "sources": ["roadkillcustoms.com", "tiresize.com"],
      "confidence": "high",
      "notes": "A-body FWD platform"
    },
    {
      "year": 1989, "make": "Buick", "model": "Century",
      "bolt_pattern": "5x115",
      "hub_bore": 70.3,
      "oem_wheel_sizes": ["14x6"],
      "oem_tire_sizes": ["185/75R14", "195/75R14"],
      "staggered": false,
      "sources": ["roadkillcustoms.com", "tiresize.com"],
      "confidence": "high",
      "notes": "A-body FWD platform"
    },
    {
      "year": 1980, "make": "Buick", "model": "Riviera",
      "bolt_pattern": "5x120.65",
      "hub_bore": 70.3,
      "oem_wheel_sizes": ["15x6", "15x7"],
      "oem_tire_sizes": ["205/75R15", "215/65R15"],
      "staggered": false,
      "sources": ["roadkillcustoms.com", "bbwheelsonline.com"],
      "confidence": "high",
      "notes": "E-body FWD personal luxury"
    },
    {
      "year": 1981, "make": "Buick", "model": "Riviera",
      "bolt_pattern": "5x120.65",
      "hub_bore": 70.3,
      "oem_wheel_sizes": ["15x6", "15x7"],
      "oem_tire_sizes": ["205/75R15", "215/65R15"],
      "staggered": false,
      "sources": ["roadkillcustoms.com", "bbwheelsonline.com"],
      "confidence": "high",
      "notes": "E-body FWD personal luxury"
    },
    {
      "year": 1982, "make": "Buick", "model": "Riviera",
      "bolt_pattern": "5x120.65",
      "hub_bore": 70.3,
      "oem_wheel_sizes": ["15x6", "15x7"],
      "oem_tire_sizes": ["205/75R15", "215/65R15"],
      "staggered": false,
      "sources": ["roadkillcustoms.com", "bbwheelsonline.com"],
      "confidence": "high",
      "notes": "E-body FWD personal luxury"
    },
    {
      "year": 1983, "make": "Buick", "model": "Riviera",
      "bolt_pattern": "5x120.65",
      "hub_bore": 70.3,
      "oem_wheel_sizes": ["15x6", "15x7"],
      "oem_tire_sizes": ["205/75R15", "215/65R15"],
      "staggered": false,
      "sources": ["roadkillcustoms.com", "bbwheelsonline.com"],
      "confidence": "high",
      "notes": "E-body FWD personal luxury"
    },
    {
      "year": 1984, "make": "Buick", "model": "Riviera",
      "bolt_pattern": "5x120.65",
      "hub_bore": 70.3,
      "oem_wheel_sizes": ["15x6", "15x7"],
      "oem_tire_sizes": ["205/75R15", "215/65R15"],
      "staggered": false,
      "sources": ["roadkillcustoms.com", "bbwheelsonline.com"],
      "confidence": "high",
      "notes": "E-body FWD personal luxury"
    },
    {
      "year": 1985, "make": "Buick", "model": "Riviera",
      "bolt_pattern": "5x120.65",
      "hub_bore": 70.3,
      "oem_wheel_sizes": ["15x6", "15x7"],
      "oem_tire_sizes": ["205/75R15", "215/65R15"],
      "staggered": false,
      "sources": ["roadkillcustoms.com", "bbwheelsonline.com"],
      "confidence": "high",
      "notes": "E-body FWD personal luxury, last year of this generation"
    },
    {
      "year": 1986, "make": "Buick", "model": "Riviera",
      "bolt_pattern": "5x115",
      "hub_bore": 70.3,
      "oem_wheel_sizes": ["15x6"],
      "oem_tire_sizes": ["205/70R15"],
      "staggered": false,
      "sources": ["roadkillcustoms.com", "tiresize.com"],
      "confidence": "high",
      "notes": "E-body FWD downsized, new platform"
    },
    {
      "year": 1987, "make": "Buick", "model": "Riviera",
      "bolt_pattern": "5x115",
      "hub_bore": 70.3,
      "oem_wheel_sizes": ["15x6"],
      "oem_tire_sizes": ["205/70R15"],
      "staggered": false,
      "sources": ["roadkillcustoms.com", "tiresize.com"],
      "confidence": "high",
      "notes": "E-body FWD"
    },
    {
      "year": 1988, "make": "Buick", "model": "Riviera",
      "bolt_pattern": "5x115",
      "hub_bore": 70.3,
      "oem_wheel_sizes": ["15x6"],
      "oem_tire_sizes": ["205/70R15"],
      "staggered": false,
      "sources": ["roadkillcustoms.com", "tiresize.com"],
      "confidence": "high",
      "notes": "E-body FWD"
    },
    {
      "year": 1989, "make": "Buick", "model": "Riviera",
      "bolt_pattern": "5x115",
      "hub_bore": 70.3,
      "oem_wheel_sizes": ["15x6"],
      "oem_tire_sizes": ["205/70R15"],
      "staggered": false,
      "sources": ["roadkillcustoms.com", "tiresize.com"],
      "confidence": "high",
      "notes": "E-body FWD"
    },
    {
      "year": 1980, "make": "Oldsmobile", "model": "88",
      "bolt_pattern": "5x127",
      "hub_bore": 78.1,
      "oem_wheel_sizes": ["15x6", "15x7"],
      "oem_tire_sizes": ["205/75R15", "215/75R15"],
      "staggered": false,
      "sources": ["roadkillcustoms.com", "tiresize.com"],
      "confidence": "high",
      "notes": "B-body RWD platform (Delta 88)"
    },
    {
      "year": 1981, "make": "Oldsmobile", "model": "88",
      "bolt_pattern": "5x127",
      "hub_bore": 78.1,
      "oem_wheel_sizes": ["15x6", "15x7"],
      "oem_tire_sizes": ["205/75R15", "215/75R15"],
      "staggered": false,
      "sources": ["roadkillcustoms.com", "tiresize.com"],
      "confidence": "high",
      "notes": "B-body RWD platform (Delta 88)"
    },
    {
      "year": 1982, "make": "Oldsmobile", "model": "88",
      "bolt_pattern": "5x127",
      "hub_bore": 78.1,
      "oem_wheel_sizes": ["15x6", "15x7"],
      "oem_tire_sizes": ["205/75R15", "215/75R15"],
      "staggered": false,
      "sources": ["roadkillcustoms.com", "tiresize.com"],
      "confidence": "high",
      "notes": "B-body RWD platform (Delta 88)"
    },
    {
      "year": 1983, "make": "Oldsmobile", "model": "88",
      "bolt_pattern": "5x127",
      "hub_bore": 78.1,
      "oem_wheel_sizes": ["15x6", "15x7"],
      "oem_tire_sizes": ["205/75R15", "215/75R15"],
      "staggered": false,
      "sources": ["roadkillcustoms.com", "tiresize.com"],
      "confidence": "high",
      "notes": "B-body RWD platform (Delta 88)"
    },
    {
      "year": 1984, "make": "Oldsmobile", "model": "88",
      "bolt_pattern": "5x127",
      "hub_bore": 78.1,
      "oem_wheel_sizes": ["15x6", "15x7"],
      "oem_tire_sizes": ["205/75R15", "215/75R15"],
      "staggered": false,
      "sources": ["roadkillcustoms.com", "tiresize.com"],
      "confidence": "high",
      "notes": "B-body RWD platform (Delta 88)"
    },
    {
      "year": 1985, "make": "Oldsmobile", "model": "88",
      "bolt_pattern": "5x127",
      "hub_bore": 78.1,
      "oem_wheel_sizes": ["15x6", "15x7"],
      "oem_tire_sizes": ["205/75R15", "215/75R15"],
      "staggered": false,
      "sources": ["roadkillcustoms.com", "tiresize.com"],
      "confidence": "high",
      "notes": "B-body RWD platform (Delta 88), last year"
    },
    {
      "year": 1986, "make": "Oldsmobile", "model": "88",
      "bolt_pattern": "5x115",
      "hub_bore": 70.3,
      "oem_wheel_sizes": ["14x6", "15x6"],
      "oem_tire_sizes": ["195/75R14", "205/70R15"],
      "staggered": false,
      "sources": ["roadkillcustoms.com", "tiresize.com"],
      "confidence": "high",
      "notes": "H-body FWD platform"
    },
    {
      "year": 1987, "make": "Oldsmobile", "model": "88",
      "bolt_pattern": "5x115",
      "hub_bore": 70.3,
      "oem_wheel_sizes": ["15x6"],
      "oem_tire_sizes": ["205/70R15"],
      "staggered": false,
      "sources": ["roadkillcustoms.com", "tiresize.com"],
      "confidence": "high",
      "notes": "H-body FWD platform"
    },
    {
      "year": 1988, "make": "Oldsmobile", "model": "88",
      "bolt_pattern": "5x115",
      "hub_bore": 70.3,
      "oem_wheel_sizes": ["15x6"],
      "oem_tire_sizes": ["205/70R15"],
      "staggered": false,
      "sources": ["roadkillcustoms.com", "tiresize.com"],
      "confidence": "high",
      "notes": "H-body FWD platform"
    },
    {
      "year": 1989, "make": "Oldsmobile", "model": "88",
      "bolt_pattern": "5x115",
      "hub_bore": 70.3,
      "oem_wheel_sizes": ["15x6"],
      "oem_tire_sizes": ["205/70R15"],
      "staggered": false,
      "sources": ["roadkillcustoms.com", "tiresize.com"],
      "confidence": "high",
      "notes": "H-body FWD platform"
    },
    {
      "year": 1980, "make": "Oldsmobile", "model": "98",
      "bolt_pattern": "5x127",
      "hub_bore": 78.1,
      "oem_wheel_sizes": ["15x6", "15x7"],
      "oem_tire_sizes": ["215/75R15", "225/70R15"],
      "staggered": false,
      "sources": ["roadkillcustoms.com", "tiresize.com"],
      "confidence": "high",
      "notes": "C-body RWD platform"
    },
    {
      "year": 1981, "make": "Oldsmobile", "model": "98",
      "bolt_pattern": "5x127",
      "hub_bore": 78.1,
      "oem_wheel_sizes": ["15x6", "15x7"],
      "oem_tire_sizes": ["215/75R15", "225/70R15"],
      "staggered": false,
      "sources": ["roadkillcustoms.com", "tiresize.com"],
      "confidence": "high",
      "notes": "C-body RWD platform"
    },
    {
      "year": 1982, "make": "Oldsmobile", "model": "98",
      "bolt_pattern": "5x127",
      "hub_bore": 78.1,
      "oem_wheel_sizes": ["15x6", "15x7"],
      "oem_tire_sizes": ["215/75R15", "225/70R15"],
      "staggered": false,
      "sources": ["roadkillcustoms.com", "tiresize.com"],
      "confidence": "high",
      "notes": "C-body RWD platform"
    },
    {
      "year": 1983, "make": "Oldsmobile", "model": "98",
      "bolt_pattern": "5x127",
      "hub_bore": 78.1,
      "oem_wheel_sizes": ["15x6", "15x7"],
      "oem_tire_sizes": ["215/75R15", "225/70R15"],
      "staggered": false,
      "sources": ["roadkillcustoms.com", "tiresize.com"],
      "confidence": "high",
      "notes": "C-body RWD platform"
    },
    {
      "year": 1984, "make": "Oldsmobile", "model": "98",
      "bolt_pattern": "5x127",
      "hub_bore": 78.1,
      "oem_wheel_sizes": ["15x6", "15x7"],
      "oem_tire_sizes": ["215/75R15", "225/70R15"],
      "staggered": false,
      "sources": ["roadkillcustoms.com", "tiresize.com"],
      "confidence": "high",
      "notes": "C-body RWD platform, last year RWD"
    },
    {
      "year": 1985, "make": "Oldsmobile", "model": "98",
      "bolt_pattern": "5x115",
      "hub_bore": 70.3,
      "oem_wheel_sizes": ["14x6", "15x6"],
      "oem_tire_sizes": ["195/75R14", "205/70R15"],
      "staggered": false,
      "sources": ["roadkillcustoms.com", "tiresize.com"],
      "confidence": "high",
      "notes": "C-body FWD platform"
    },
    {
      "year": 1986, "make": "Oldsmobile", "model": "98",
      "bolt_pattern": "5x115",
      "hub_bore": 70.3,
      "oem_wheel_sizes": ["15x6"],
      "oem_tire_sizes": ["205/70R15"],
      "staggered": false,
      "sources": ["roadkillcustoms.com", "tiresize.com"],
      "confidence": "high",
      "notes": "C-body FWD platform"
    },
    {
      "year": 1987, "make": "Oldsmobile", "model": "98",
      "bolt_pattern": "5x115",
      "hub_bore": 70.3,
      "oem_wheel_sizes": ["15x6"],
      "oem_tire_sizes": ["205/70R15"],
      "staggered": false,
      "sources": ["roadkillcustoms.com", "tiresize.com"],
      "confidence": "high",
      "notes": "C-body FWD platform"
    },
    {
      "year": 1988, "make": "Oldsmobile", "model": "98",
      "bolt_pattern": "5x115",
      "hub_bore": 70.3,
      "oem_wheel_sizes": ["15x6"],
      "oem_tire_sizes": ["205/70R15"],
      "staggered": false,
      "sources": ["roadkillcustoms.com", "tiresize.com"],
      "confidence": "high",
      "notes": "C-body FWD platform"
    },
    {
      "year": 1989, "make": "Oldsmobile", "model": "98",
      "bolt_pattern": "5x115",
      "hub_bore": 70.3,
      "oem_wheel_sizes": ["15x6"],
      "oem_tire_sizes": ["205/70R15"],
      "staggered": false,
      "sources": ["roadkillcustoms.com", "tiresize.com"],
      "confidence": "high",
      "notes": "C-body FWD platform"
    },
    {
      "year": 1980, "make": "Oldsmobile", "model": "Toronado",
      "bolt_pattern": "5x120.65",
      "hub_bore": 70.3,
      "oem_wheel_sizes": ["15x6", "15x7"],
      "oem_tire_sizes": ["205/75R15", "215/65R15"],
      "staggered": false,
      "sources": ["tirewheelguide.com", "bbwheelsonline.com"],
      "confidence": "high",
      "notes": "E-body FWD personal luxury"
    },
    {
      "year": 1981, "make": "Oldsmobile", "model": "Toronado",
      "bolt_pattern": "5x120.65",
      "hub_bore": 70.3,
      "oem_wheel_sizes": ["15x6", "15x7"],
      "oem_tire_sizes": ["205/75R15", "215/65R15"],
      "staggered": false,
      "sources": ["tirewheelguide.com", "bbwheelsonline.com"],
      "confidence": "high",
      "notes": "E-body FWD personal luxury"
    },
    {
      "year": 1982, "make": "Oldsmobile", "model": "Toronado",
      "bolt_pattern": "5x120.65",
      "hub_bore": 70.3,
      "oem_wheel_sizes": ["15x6", "15x7"],
      "oem_tire_sizes": ["205/75R15", "215/65R15"],
      "staggered": false,
      "sources": ["tirewheelguide.com", "bbwheelsonline.com"],
      "confidence": "high",
      "notes": "E-body FWD personal luxury"
    },
    {
      "year": 1983, "make": "Oldsmobile", "model": "Toronado",
      "bolt_pattern": "5x120.65",
      "hub_bore": 70.3,
      "oem_wheel_sizes": ["15x6", "15x7"],
      "oem_tire_sizes": ["205/75R15", "215/65R15"],
      "staggered": false,
      "sources": ["tirewheelguide.com", "bbwheelsonline.com"],
      "confidence": "high",
      "notes": "E-body FWD personal luxury"
    },
    {
      "year": 1984, "make": "Oldsmobile", "model": "Toronado",
      "bolt_pattern": "5x120.65",
      "hub_bore": 70.3,
      "oem_wheel_sizes": ["15x6", "15x7"],
      "oem_tire_sizes": ["205/75R15", "215/65R15"],
      "staggered": false,
      "sources": ["tirewheelguide.com", "bbwheelsonline.com"],
      "confidence": "high",
      "notes": "E-body FWD personal luxury"
    },
    {
      "year": 1985, "make": "Oldsmobile", "model": "Toronado",
      "bolt_pattern": "5x120.65",
      "hub_bore": 70.3,
      "oem_wheel_sizes": ["15x6", "15x7"],
      "oem_tire_sizes": ["205/75R15", "215/65R15"],
      "staggered": false,
      "sources": ["tirewheelguide.com", "bbwheelsonline.com"],
      "confidence": "high",
      "notes": "E-body FWD personal luxury, last year of this generation"
    },
    {
      "year": 1986, "make": "Oldsmobile", "model": "Toronado",
      "bolt_pattern": "5x115",
      "hub_bore": 70.3,
      "oem_wheel_sizes": ["15x6"],
      "oem_tire_sizes": ["205/70R15"],
      "staggered": false,
      "sources": ["tirewheelguide.com", "roadkillcustoms.com"],
      "confidence": "high",
      "notes": "E-body FWD downsized"
    },
    {
      "year": 1987, "make": "Oldsmobile", "model": "Toronado",
      "bolt_pattern": "5x115",
      "hub_bore": 70.3,
      "oem_wheel_sizes": ["15x6"],
      "oem_tire_sizes": ["205/70R15"],
      "staggered": false,
      "sources": ["tirewheelguide.com", "roadkillcustoms.com"],
      "confidence": "high",
      "notes": "E-body FWD"
    },
    {
      "year": 1988, "make": "Oldsmobile", "model": "Toronado",
      "bolt_pattern": "5x115",
      "hub_bore": 70.3,
      "oem_wheel_sizes": ["15x6"],
      "oem_tire_sizes": ["205/70R15"],
      "staggered": false,
      "sources": ["tirewheelguide.com", "roadkillcustoms.com"],
      "confidence": "high",
      "notes": "E-body FWD"
    },
    {
      "year": 1989, "make": "Oldsmobile", "model": "Toronado",
      "bolt_pattern": "5x115",
      "hub_bore": 70.3,
      "oem_wheel_sizes": ["15x6"],
      "oem_tire_sizes": ["205/70R15"],
      "staggered": false,
      "sources": ["tirewheelguide.com", "roadkillcustoms.com"],
      "confidence": "high",
      "notes": "E-body FWD"
    },
    {
      "year": 1982, "make": "Oldsmobile", "model": "Ciera",
      "bolt_pattern": "5x115",
      "hub_bore": 70.3,
      "oem_wheel_sizes": ["13x5.5", "14x6"],
      "oem_tire_sizes": ["185/80R13", "195/75R14"],
      "staggered": false,
      "sources": ["tiresize.com", "roadkillcustoms.com"],
      "confidence": "high",
      "notes": "A-body FWD platform (Cutlass Ciera)"
    },
    {
      "year": 1983, "make": "Oldsmobile", "model": "Ciera",
      "bolt_pattern": "5x115",
      "hub_bore": 70.3,
      "oem_wheel_sizes": ["14x6"],
      "oem_tire_sizes": ["185/75R14", "195/75R14"],
      "staggered": false,
      "sources": ["tiresize.com", "roadkillcustoms.com"],
      "confidence": "high",
      "notes": "A-body FWD platform (Cutlass Ciera)"
    },
    {
      "year": 1984, "make": "Oldsmobile", "model": "Ciera",
      "bolt_pattern": "5x115",
      "hub_bore": 70.3,
      "oem_wheel_sizes": ["14x6"],
      "oem_tire_sizes": ["185/75R14", "195/75R14"],
      "staggered": false,
      "sources": ["tiresize.com", "roadkillcustoms.com"],
      "confidence": "high",
      "notes": "A-body FWD platform (Cutlass Ciera)"
    },
    {
      "year": 1985, "make": "Oldsmobile", "model": "Ciera",
      "bolt_pattern": "5x115",
      "hub_bore": 70.3,
      "oem_wheel_sizes": ["14x6"],
      "oem_tire_sizes": ["185/75R14", "195/75R14"],
      "staggered": false,
      "sources": ["tiresize.com", "roadkillcustoms.com"],
      "confidence": "high",
      "notes": "A-body FWD platform (Cutlass Ciera)"
    },
    {
      "year": 1986, "make": "Oldsmobile", "model": "Ciera",
      "bolt_pattern": "5x115",
      "hub_bore": 70.3,
      "oem_wheel_sizes": ["14x6"],
      "oem_tire_sizes": ["185/75R14", "195/75R14"],
      "staggered": false,
      "sources": ["tiresize.com", "roadkillcustoms.com"],
      "confidence": "high",
      "notes": "A-body FWD platform (Cutlass Ciera)"
    },
    {
      "year": 1987, "make": "Oldsmobile", "model": "Ciera",
      "bolt_pattern": "5x115",
      "hub_bore": 70.3,
      "oem_wheel_sizes": ["14x6"],
      "oem_tire_sizes": ["185/75R14", "195/75R14"],
      "staggered": false,
      "sources": ["tiresize.com", "roadkillcustoms.com"],
      "confidence": "high",
      "notes": "A-body FWD platform (Cutlass Ciera)"
    },
    {
      "year": 1988, "make": "Oldsmobile", "model": "Ciera",
      "bolt_pattern": "5x115",
      "hub_bore": 70.3,
      "oem_wheel_sizes": ["14x6"],
      "oem_tire_sizes": ["185/75R14", "195/75R14"],
      "staggered": false,
      "sources": ["tiresize.com", "roadkillcustoms.com"],
      "confidence": "high",
      "notes": "A-body FWD platform (Cutlass Ciera)"
    },
    {
      "year": 1989, "make": "Oldsmobile", "model": "Ciera",
      "bolt_pattern": "5x115",
      "hub_bore": 70.3,
      "oem_wheel_sizes": ["14x6"],
      "oem_tire_sizes": ["185/75R14", "195/75R14"],
      "staggered": false,
      "sources": ["tiresize.com", "roadkillcustoms.com"],
      "confidence": "high",
      "notes": "A-body FWD platform (Cutlass Ciera)"
    },
    {
      "year": 1980, "make": "Cadillac", "model": "DeVille",
      "bolt_pattern": "5x127",
      "hub_bore": 78.1,
      "oem_wheel_sizes": ["15x6"],
      "oem_tire_sizes": ["205/75R15", "215/75R15"],
      "staggered": false,
      "sources": ["roadkillcustoms.com", "bbwheelsonline.com"],
      "confidence": "high",
      "notes": "C-body RWD platform"
    },
    {
      "year": 1981, "make": "Cadillac", "model": "DeVille",
      "bolt_pattern": "5x127",
      "hub_bore": 78.1,
      "oem_wheel_sizes": ["15x6"],
      "oem_tire_sizes": ["205/75R15", "215/75R15"],
      "staggered": false,
      "sources": ["roadkillcustoms.com", "bbwheelsonline.com"],
      "confidence": "high",
      "notes": "C-body RWD platform"
    },
    {
      "year": 1982, "make": "Cadillac", "model": "DeVille",
      "bolt_pattern": "5x127",
      "hub_bore": 78.1,
      "oem_wheel_sizes": ["15x6"],
      "oem_tire_sizes": ["205/75R15", "215/75R15"],
      "staggered": false,
      "sources": ["roadkillcustoms.com", "bbwheelsonline.com"],
      "confidence": "high",
      "notes": "C-body RWD platform"
    },
    {
      "year": 1983, "make": "Cadillac", "model": "DeVille",
      "bolt_pattern": "5x127",
      "hub_bore": 78.1,
      "oem_wheel_sizes": ["15x6"],
      "oem_tire_sizes": ["205/75R15", "215/75R15"],
      "staggered": false,
      "sources": ["roadkillcustoms.com", "bbwheelsonline.com"],
      "confidence": "high",
      "notes": "C-body RWD platform"
    },
    {
      "year": 1984, "make": "Cadillac", "model": "DeVille",
      "bolt_pattern": "5x127",
      "hub_bore": 78.1,
      "oem_wheel_sizes": ["15x6"],
      "oem_tire_sizes": ["205/75R15", "215/75R15"],
      "staggered": false,
      "sources": ["roadkillcustoms.com", "bbwheelsonline.com"],
      "confidence": "high",
      "notes": "C-body RWD platform, last year RWD"
    },
    {
      "year": 1985, "make": "Cadillac", "model": "DeVille",
      "bolt_pattern": "5x115",
      "hub_bore": 70.3,
      "oem_wheel_sizes": ["14x6", "15x6"],
      "oem_tire_sizes": ["195/75R14", "205/70R15"],
      "staggered": false,
      "sources": ["roadkillcustoms.com", "cadillacforums.com"],
      "confidence": "high",
      "notes": "C-body FWD platform"
    },
    {
      "year": 1986, "make": "Cadillac", "model": "DeVille",
      "bolt_pattern": "5x115",
      "hub_bore": 70.3,
      "oem_wheel_sizes": ["14x6", "15x6"],
      "oem_tire_sizes": ["195/75R14", "205/70R15"],
      "staggered": false,
      "sources": ["roadkillcustoms.com", "cadillacforums.com"],
      "confidence": "high",
      "notes": "C-body FWD platform"
    },
    {
      "year": 1987, "make": "Cadillac", "model": "DeVille",
      "bolt_pattern": "5x115",
      "hub_bore": 70.3,
      "oem_wheel_sizes": ["15x6"],
      "oem_tire_sizes": ["205/70R15"],
      "staggered": false,
      "sources": ["roadkillcustoms.com", "cadillacforums.com"],
      "confidence": "high",
      "notes": "C-body FWD platform"
    },
    {
      "year": 1988, "make": "Cadillac", "model": "DeVille",
      "bolt_pattern": "5x115",
      "hub_bore": 70.3,
      "oem_wheel_sizes": ["15x6"],
      "oem_tire_sizes": ["205/70R15"],
      "staggered": false,
      "sources": ["roadkillcustoms.com", "cadillacforums.com"],
      "confidence": "high",
      "notes": "C-body FWD platform"
    },
    {
      "year": 1989, "make": "Cadillac", "model": "DeVille",
      "bolt_pattern": "5x115",
      "hub_bore": 70.3,
      "oem_wheel_sizes": ["15x6"],
      "oem_tire_sizes": ["205/70R15"],
      "staggered": false,
      "sources": ["roadkillcustoms.com", "cadillacforums.com"],
      "confidence": "high",
      "notes": "C-body FWD platform"
    },
    {
      "year": 1980, "make": "Cadillac", "model": "Fleetwood",
      "bolt_pattern": "5x127",
      "hub_bore": 78.1,
      "oem_wheel_sizes": ["15x6", "15x7"],
      "oem_tire_sizes": ["205/75R15", "215/75R15"],
      "staggered": false,
      "sources": ["roadkillcustoms.com", "cadillacforums.com"],
      "confidence": "high",
      "notes": "C-body RWD platform"
    },
    {
      "year": 1981, "make": "Cadillac", "model": "Fleetwood",
      "bolt_pattern": "5x127",
      "hub_bore": 78.1,
      "oem_wheel_sizes": ["15x6", "15x7"],
      "oem_tire_sizes": ["205/75R15", "215/75R15"],
      "staggered": false,
      "sources": ["roadkillcustoms.com", "cadillacforums.com"],
      "confidence": "high",
      "notes": "C-body RWD platform"
    },
    {
      "year": 1982, "make": "Cadillac", "model": "Fleetwood",
      "bolt_pattern": "5x127",
      "hub_bore": 78.1,
      "oem_wheel_sizes": ["15x6", "15x7"],
      "oem_tire_sizes": ["205/75R15", "215/75R15"],
      "staggered": false,
      "sources": ["roadkillcustoms.com", "cadillacforums.com"],
      "confidence": "high",
      "notes": "C-body RWD platform"
    },
    {
      "year": 1983, "make": "Cadillac", "model": "Fleetwood",
      "bolt_pattern": "5x127",
      "hub_bore": 78.1,
      "oem_wheel_sizes": ["15x6", "15x7"],
      "oem_tire_sizes": ["205/75R15", "215/75R15"],
      "staggered": false,
      "sources": ["roadkillcustoms.com", "cadillacforums.com"],
      "confidence": "high",
      "notes": "C-body RWD platform"
    },
    {
      "year": 1984, "make": "Cadillac", "model": "Fleetwood",
      "bolt_pattern": "5x127",
      "hub_bore": 78.1,
      "oem_wheel_sizes": ["15x6", "15x7"],
      "oem_tire_sizes": ["205/75R15", "215/75R15"],
      "staggered": false,
      "sources": ["roadkillcustoms.com", "cadillacforums.com"],
      "confidence": "high",
      "notes": "C-body RWD platform, last year RWD (until D-body 1993)"
    },
    {
      "year": 1985, "make": "Cadillac", "model": "Fleetwood",
      "bolt_pattern": "5x115",
      "hub_bore": 70.3,
      "oem_wheel_sizes": ["14x6", "15x6"],
      "oem_tire_sizes": ["195/75R14", "205/70R15"],
      "staggered": false,
      "sources": ["roadkillcustoms.com", "cadillacforums.com"],
      "confidence": "high",
      "notes": "C-body FWD platform"
    },
    {
      "year": 1986, "make": "Cadillac", "model": "Fleetwood",
      "bolt_pattern": "5x115",
      "hub_bore": 70.3,
      "oem_wheel_sizes": ["14x6", "15x6"],
      "oem_tire_sizes": ["195/75R14", "205/70R15"],
      "staggered": false,
      "sources": ["roadkillcustoms.com", "cadillacforums.com"],
      "confidence": "high",
      "notes": "C-body FWD platform"
    },
    {
      "year": 1987, "make": "Cadillac", "model": "Fleetwood",
      "bolt_pattern": "5x115",
      "hub_bore": 70.3,
      "oem_wheel_sizes": ["15x6"],
      "oem_tire_sizes": ["205/70R15"],
      "staggered": false,
      "sources": ["roadkillcustoms.com", "cadillacforums.com"],
      "confidence": "high",
      "notes": "C-body FWD platform"
    },
    {
      "year": 1988, "make": "Cadillac", "model": "Fleetwood",
      "bolt_pattern": "5x115",
      "hub_bore": 70.3,
      "oem_wheel_sizes": ["15x6"],
      "oem_tire_sizes": ["205/70R15"],
      "staggered": false,
      "sources": ["roadkillcustoms.com", "cadillacforums.com"],
      "confidence": "high",
      "notes": "C-body FWD platform"
    },
    {
      "year": 1989, "make": "Cadillac", "model": "Fleetwood",
      "bolt_pattern": "5x115",
      "hub_bore": 70.3,
      "oem_wheel_sizes": ["15x6"],
      "oem_tire_sizes": ["205/70R15"],
      "staggered": false,
      "sources": ["roadkillcustoms.com", "cadillacforums.com"],
      "confidence": "high",
      "notes": "C-body FWD platform"
    },
    {
      "year": 1980, "make": "Cadillac", "model": "Eldorado",
      "bolt_pattern": "5x120.65",
      "hub_bore": 70.3,
      "oem_wheel_sizes": ["15x6", "15x7"],
      "oem_tire_sizes": ["205/75R15", "215/65R15"],
      "staggered": false,
      "sources": ["roadkillcustoms.com", "cadillacforums.com"],
      "confidence": "high",
      "notes": "E-body FWD personal luxury"
    },
    {
      "year": 1981, "make": "Cadillac", "model": "Eldorado",
      "bolt_pattern": "5x120.65",
      "hub_bore": 70.3,
      "oem_wheel_sizes": ["15x6", "15x7"],
      "oem_tire_sizes": ["205/75R15", "215/65R15"],
      "staggered": false,
      "sources": ["roadkillcustoms.com", "cadillacforums.com"],
      "confidence": "high",
      "notes": "E-body FWD personal luxury"
    },
    {
      "year": 1982, "make": "Cadillac", "model": "Eldorado",
      "bolt_pattern": "5x120.65",
      "hub_bore": 70.3,
      "oem_wheel_sizes": ["15x6", "15x7"],
      "oem_tire_sizes": ["205/75R15", "215/65R15"],
      "staggered": false,
      "sources": ["roadkillcustoms.com", "cadillacforums.com"],
      "confidence": "high",
      "notes": "E-body FWD personal luxury"
    },
    {
      "year": 1983, "make": "Cadillac", "model": "Eldorado",
      "bolt_pattern": "5x120.65",
      "hub_bore": 70.3,
      "oem_wheel_sizes": ["15x6", "15x7"],
      "oem_tire_sizes": ["205/75R15", "215/65R15"],
      "staggered": false,
      "sources": ["roadkillcustoms.com", "cadillacforums.com"],
      "confidence": "high",
      "notes": "E-body FWD personal luxury"
    },
    {
      "year": 1984, "make": "Cadillac", "model": "Eldorado",
      "bolt_pattern": "5x120.65",
      "hub_bore": 70.3,
      "oem_wheel_sizes": ["15x6", "15x7"],
      "oem_tire_sizes": ["205/75R15", "215/65R15"],
      "staggered": false,
      "sources": ["roadkillcustoms.com", "cadillacforums.com"],
      "confidence": "high",
      "notes": "E-body FWD personal luxury"
    },
    {
      "year": 1985, "make": "Cadillac", "model": "Eldorado",
      "bolt_pattern": "5x120.65",
      "hub_bore": 70.3,
      "oem_wheel_sizes": ["15x6", "15x7"],
      "oem_tire_sizes": ["205/75R15", "215/65R15"],
      "staggered": false,
      "sources": ["roadkillcustoms.com", "cadillacforums.com"],
      "confidence": "high",
      "notes": "E-body FWD personal luxury, last year of this generation"
    },
    {
      "year": 1986, "make": "Cadillac", "model": "Eldorado",
      "bolt_pattern": "5x115",
      "hub_bore": 70.3,
      "oem_wheel_sizes": ["15x6", "16x7"],
      "oem_tire_sizes": ["205/70R15", "215/65R15"],
      "staggered": false,
      "sources": ["roadkillcustoms.com", "cadillacforums.com"],
      "confidence": "high",
      "notes": "E-body FWD downsized"
    },
    {
      "year": 1987, "make": "Cadillac", "model": "Eldorado",
      "bolt_pattern": "5x115",
      "hub_bore": 70.3,
      "oem_wheel_sizes": ["15x6", "16x7"],
      "oem_tire_sizes": ["205/70R15", "215/65R15"],
      "staggered": false,
      "sources": ["roadkillcustoms.com", "cadillacforums.com"],
      "confidence": "high",
      "notes": "E-body FWD"
    },
    {
      "year": 1988, "make": "Cadillac", "model": "Eldorado",
      "bolt_pattern": "5x115",
      "hub_bore": 70.3,
      "oem_wheel_sizes": ["15x6", "16x7"],
      "oem_tire_sizes": ["205/70R15", "215/65R15"],
      "staggered": false,
      "sources": ["roadkillcustoms.com", "cadillacforums.com"],
      "confidence": "high",
      "notes": "E-body FWD"
    },
    {
      "year": 1989, "make": "Cadillac", "model": "Eldorado",
      "bolt_pattern": "5x115",
      "hub_bore": 70.3,
      "oem_wheel_sizes": ["15x6", "16x7"],
      "oem_tire_sizes": ["205/70R15", "215/65R15"],
      "staggered": false,
      "sources": ["roadkillcustoms.com", "cadillacforums.com"],
      "confidence": "high",
      "notes": "E-body FWD"
    },
    {
      "year": 1980, "make": "Cadillac", "model": "Seville",
      "bolt_pattern": "5x120.65",
      "hub_bore": 70.3,
      "oem_wheel_sizes": ["15x6"],
      "oem_tire_sizes": ["205/75R15"],
      "staggered": false,
      "sources": ["roadkillcustoms.com", "cadillacforums.com"],
      "confidence": "high",
      "notes": "K-body FWD platform"
    },
    {
      "year": 1981, "make": "Cadillac", "model": "Seville",
      "bolt_pattern": "5x120.65",
      "hub_bore": 70.3,
      "oem_wheel_sizes": ["15x6"],
      "oem_tire_sizes": ["205/75R15"],
      "staggered": false,
      "sources": ["roadkillcustoms.com", "cadillacforums.com"],
      "confidence": "high",
      "notes": "K-body FWD platform"
    },
    {
      "year": 1982, "make": "Cadillac", "model": "Seville",
      "bolt_pattern": "5x120.65",
      "hub_bore": 70.3,
      "oem_wheel_sizes": ["15x6"],
      "oem_tire_sizes": ["205/75R15"],
      "staggered": false,
      "sources": ["roadkillcustoms.com", "cadillacforums.com"],
      "confidence": "high",
      "notes": "K-body FWD platform"
    },
    {
      "year": 1983, "make": "Cadillac", "model": "Seville",
      "bolt_pattern": "5x120.65",
      "hub_bore": 70.3,
      "oem_wheel_sizes": ["15x6"],
      "oem_tire_sizes": ["205/75R15"],
      "staggered": false,
      "sources": ["roadkillcustoms.com", "cadillacforums.com"],
      "confidence": "high",
      "notes": "K-body FWD platform"
    },
    {
      "year": 1984, "make": "Cadillac", "model": "Seville",
      "bolt_pattern": "5x120.65",
      "hub_bore": 70.3,
      "oem_wheel_sizes": ["15x6"],
      "oem_tire_sizes": ["205/75R15"],
      "staggered": false,
      "sources": ["roadkillcustoms.com", "cadillacforums.com"],
      "confidence": "high",
      "notes": "K-body FWD platform"
    },
    {
      "year": 1985, "make": "Cadillac", "model": "Seville",
      "bolt_pattern": "5x120.65",
      "hub_bore": 70.3,
      "oem_wheel_sizes": ["15x6"],
      "oem_tire_sizes": ["205/75R15"],
      "staggered": false,
      "sources": ["roadkillcustoms.com", "cadillacforums.com"],
      "confidence": "high",
      "notes": "K-body FWD platform, last year of this generation"
    },
    {
      "year": 1986, "make": "Cadillac", "model": "Seville",
      "bolt_pattern": "5x115",
      "hub_bore": 70.3,
      "oem_wheel_sizes": ["14x6", "15x6"],
      "oem_tire_sizes": ["195/75R14", "205/70R15"],
      "staggered": false,
      "sources": ["roadkillcustoms.com", "cadillacforums.com"],
      "confidence": "high",
      "notes": "K-body FWD downsized"
    },
    {
      "year": 1987, "make": "Cadillac", "model": "Seville",
      "bolt_pattern": "5x115",
      "hub_bore": 70.3,
      "oem_wheel_sizes": ["15x6"],
      "oem_tire_sizes": ["205/70R15"],
      "staggered": false,
      "sources": ["roadkillcustoms.com", "cadillacforums.com"],
      "confidence": "high",
      "notes": "K-body FWD"
    },
    {
      "year": 1988, "make": "Cadillac", "model": "Seville",
      "bolt_pattern": "5x115",
      "hub_bore": 70.3,
      "oem_wheel_sizes": ["15x6"],
      "oem_tire_sizes": ["205/70R15"],
      "staggered": false,
      "sources": ["roadkillcustoms.com", "cadillacforums.com"],
      "confidence": "high",
      "notes": "K-body FWD"
    },
    {
      "year": 1989, "make": "Cadillac", "model": "Seville",
      "bolt_pattern": "5x115",
      "hub_bore": 70.3,
      "oem_wheel_sizes": ["15x6"],
      "oem_tire_sizes": ["205/70R15"],
      "staggered": false,
      "sources": ["roadkillcustoms.com", "cadillacforums.com"],
      "confidence": "high",
      "notes": "K-body FWD"
    }
  ],
  "platformSummary": {
    "B-body_RWD": {
      "vehicles": ["Caprice", "Impala", "Bonneville 80-81", "LeSabre 80-85", "Delta 88 80-85"],
      "bolt_pattern": "5x127",
      "hub_bore": 78.1,
      "typical_tires": ["205/75R15", "215/75R15", "225/70R15"]
    },
    "A-body_FWD": {
      "vehicles": ["Celebrity", "Century", "Ciera", "6000"],
      "bolt_pattern": "5x115",
      "hub_bore": 70.3,
      "typical_tires": ["185/75R14", "195/75R14"]
    },
    "J-body": {
      "vehicles": ["Cavalier"],
      "bolt_pattern": "5x100",
      "hub_bore": 57.1,
      "typical_tires": ["175/80R13", "185/80R13", "195/70R14"]
    },
    "H-body_FWD": {
      "vehicles": ["Bonneville 87+", "LeSabre 86+", "88 86+", "98 85+"],
      "bolt_pattern": "5x115",
      "hub_bore": 70.3,
      "typical_tires": ["205/70R15"]
    },
    "E-body_1979-85": {
      "vehicles": ["Riviera", "Toronado", "Eldorado"],
      "bolt_pattern": "5x120.65",
      "hub_bore": 70.3,
      "typical_tires": ["205/75R15", "215/65R15"]
    },
    "E-body_1986+": {
      "vehicles": ["Riviera 86+", "Toronado 86+", "Eldorado 86+"],
      "bolt_pattern": "5x115",
      "hub_bore": 70.3,
      "typical_tires": ["205/70R15", "215/65R15"]
    },
    "C-body_RWD": {
      "vehicles": ["DeVille 80-84", "Fleetwood 80-84", "98 80-84"],
      "bolt_pattern": "5x127",
      "hub_bore": 78.1,
      "typical_tires": ["205/75R15", "215/75R15"]
    },
    "C-body_FWD": {
      "vehicles": ["DeVille 85+", "Fleetwood 85+"],
      "bolt_pattern": "5x115",
      "hub_bore": 70.3,
      "typical_tires": ["205/70R15"]
    },
    "K-body_1980-85": {
      "vehicles": ["Seville 80-85"],
      "bolt_pattern": "5x120.65",
      "hub_bore": 70.3,
      "typical_tires": ["205/75R15"]
    },
    "K-body_1986+": {
      "vehicles": ["Seville 86+"],
      "bolt_pattern": "5x115",
      "hub_bore": 70.3,
      "typical_tires": ["205/70R15"]
    },
    "G-body": {
      "vehicles": ["Bonneville 82-86"],
      "bolt_pattern": "5x120.65",
      "hub_bore": 70.3,
      "typical_tires": ["195/75R14", "205/70R14"]
    }
  }
}
