{
  "id": "d674_blitz_1775898329534",
  "createdAt": "2026-04-11T09:05:30.207Z",
  "wheel": {
    "sku": "D67417907545",
    "brand": "Fuel 1PC",
    "styleName": "D674 BLITZ",
    "finish": "BLITZ 17X9 5X5.0 71.5 MBT -12",
    "size": "17x9",
    "boltPattern": "5X5.0",
    "price": 277
  },
  "vehicle": {
    "year": 2024,
    "make": "Tesla",
    "model": "Model Y",
    "type": "ev"
  },
  "imagePath": "C:\\Users\\Scott-Pc\\backup clawd\\warehouse-tire-site\\scripts\\social-content\\output\\d674_blitz_1775898329534.png",
  "caption": "Transform your ev with the Fuel 1PC D674 BLITZ 🛞\n\n📐 17x9\n🔩 5X5.0\n↔️ -12mm offset\n✨ BLITZ 17X9 5X5.0 71.5 MBT -12\n\n$277/wheel\n\n🛒 https://shop.warehousetiredirect.com/wheels/D67417907545\n\n#wheels #rims #customwheels #wheelgoals #wheelwednesday #ev #electricvehicle #tesla #fuel1pc #warehousetiredirect",
  "productUrl": "https://shop.warehousetiredirect.com/wheels/D67417907545",
  "platforms": {
    "facebook": {
      "caption": "Transform your ev with the Fuel 1PC D674 BLITZ 🛞\n\n📐 17x9\n🔩 5X5.0\n↔️ -12mm offset\n✨ BLITZ 17X9 5X5.0 71.5 MBT -12\n\n$277/wheel\n\n🛒 https://shop.warehousetiredirect.com/wheels/D67417907545\n\n#wheels #rims #customwheels #wheelgoals #wheelwednesday #ev #electricvehicle #tesla #fuel1pc #warehousetiredirect",
      "imagePath": "C:\\Users\\Scott-Pc\\backup clawd\\warehouse-tire-site\\scripts\\social-content\\output\\d674_blitz_1775898329534.png"
    },
    "tiktok": {
      "caption": "Transform your ev with the Fuel 1PC D674 BLITZ 🛞\n\n📐 17x9\n🔩 5X5.0\n↔️ -12mm offset\n✨ BLITZ 17X9 5X5.0 71.5 MBT -12\n\n$277/wheel\n\n🛒 https://shop.wareh...",
      "imagePath": "C:\\Users\\Scott-Pc\\backup clawd\\warehouse-tire-site\\scripts\\social-content\\output\\d674_blitz_1775898329534.png"
    },
    "instagram": {
      "caption": "Transform your ev with the Fuel 1PC D674 BLITZ 🛞\n\n📐 17x9\n🔩 5X5.0\n↔️ -12mm offset\n✨ BLITZ 17X9 5X5.0 71.5 MBT -12\n\n$277/wheel\n\n🛒 https://shop.warehousetiredirect.com/wheels/D67417907545\n\n#wheels #rims #customwheels #wheelgoals #wheelwednesday #ev #electricvehicle #tesla #fuel1pc #warehousetiredirect",
      "imagePath": "C:\\Users\\Scott-Pc\\backup clawd\\warehouse-tire-site\\scripts\\social-content\\output\\d674_blitz_1775898329534.png"
    }
  }
}