{
  "id": "rc209_rps_1776776402221",
  "createdAt": "2026-04-21T13:00:02.688Z",
  "wheel": {
    "sku": "RC209ZX19955222",
    "brand": "Rotiform",
    "styleName": "RC209 RPS",
    "finish": "RPS 19X9.5 5X120 74 +22 B-BRNZ",
    "size": "19x9.5",
    "boltPattern": "5X120",
    "price": 427
  },
  "vehicle": {
    "year": 2024,
    "make": "Chevrolet",
    "model": "Camaro",
    "type": "muscle",
    "boltPatterns": [
      "5X120"
    ]
  },
  "imagePath": "C:\\Users\\Scott-Pc\\backup clawd\\warehouse-tire-site\\scripts\\social-content\\output\\rc209_rps_1776776402221.png",
  "caption": "Weekend project? ✅\n\nRotiform RC209 RPS\n📐 19x9.5\n🔩 5X120\n↔️ 22mm offset\n✨ RPS 19X9.5 5X120 74 +22 B-BRNZ\n\nOnly $427/wheel\n\n🛒 Get yours: https://shop.warehousetiredirect.com/wheels/RC209ZX19955222\n\n#wheels #rims #customwheels #wheelgoals #wheelwednesday #musclecar #americanmuscle #v8 #rotiform #warehousetiredirect",
  "productUrl": "https://shop.warehousetiredirect.com/wheels/RC209ZX19955222",
  "platforms": {
    "facebook": {
      "caption": "Weekend project? ✅\n\nRotiform RC209 RPS\n📐 19x9.5\n🔩 5X120\n↔️ 22mm offset\n✨ RPS 19X9.5 5X120 74 +22 B-BRNZ\n\nOnly $427/wheel\n\n🛒 Get yours: https://shop.warehousetiredirect.com/wheels/RC209ZX19955222\n\n#wheels #rims #customwheels #wheelgoals #wheelwednesday #musclecar #americanmuscle #v8 #rotiform #warehousetiredirect",
      "imagePath": "C:\\Users\\Scott-Pc\\backup clawd\\warehouse-tire-site\\scripts\\social-content\\output\\rc209_rps_1776776402221.png"
    },
    "tiktok": {
      "caption": "Weekend project? ✅\n\nRotiform RC209 RPS\n📐 19x9.5\n🔩 5X120\n↔️ 22mm offset\n✨ RPS 19X9.5 5X120 74 +22 B-BRNZ\n\nOnly $427/wheel\n\n🛒 Get yours: https://shop...",
      "imagePath": "C:\\Users\\Scott-Pc\\backup clawd\\warehouse-tire-site\\scripts\\social-content\\output\\rc209_rps_1776776402221.png"
    },
    "instagram": {
      "caption": "Weekend project? ✅\n\nRotiform RC209 RPS\n📐 19x9.5\n🔩 5X120\n↔️ 22mm offset\n✨ RPS 19X9.5 5X120 74 +22 B-BRNZ\n\nOnly $427/wheel\n\n🛒 Get yours: https://shop.warehousetiredirect.com/wheels/RC209ZX19955222\n\n#wheels #rims #customwheels #wheelgoals #wheelwednesday #musclecar #americanmuscle #v8 #rotiform #warehousetiredirect",
      "imagePath": "C:\\Users\\Scott-Pc\\backup clawd\\warehouse-tire-site\\scripts\\social-content\\output\\rc209_rps_1776776402221.png"
    }
  }
}